{
  "lastUpdated": "2026-02-24T22:55:33.170Z",
  "enhancements": [
    {
      "date": "2026-02-22T02:46:32.210Z",
      "action": "Added unit tests for core module"
    },
    {
      "date": "2026-02-22T08:40:58.183Z",
      "action": "Optimized algorithm performance"
    },
    {
      "date": "2026-02-22T15:57:03.869Z",
      "action": "Added unit tests for core module"
    },
    {
      "date": "2026-02-22T19:49:45.699Z",
      "action": "Improved documentation coverage"
    },
    {
      "date": "2026-02-23T04:52:17.106Z",
      "action": "Enhanced logging verbosity"
    },
    {
      "date": "2026-02-23T07:59:13.950Z",
      "action": "Updated dependency versions"
    },
    {
      "date": "2026-02-23T09:42:30.816Z",
      "action": "Updated dependency versions"
    },
    {
      "date": "2026-02-23T10:34:28.379Z",
      "action": "Enhanced logging verbosity"
    },
    {
      "date": "2026-02-23T15:57:31.211Z",
      "action": "Added new data source integration"
    },
    {
      "date": "2026-02-23T21:09:02.183Z",
      "action": "Optimized algorithm performance"
    },
    {
      "date": "2026-02-24T11:47:29.935Z",
      "action": "Updated dependency versions"
    },
    {
      "date": "2026-02-24T14:42:05.766Z",
      "action": "Added unit tests for core module"
    },
    {
      "date": "2026-02-24T22:19:26.225Z",
      "action": "Improved documentation coverage"
    },
    {
      "date": "2026-02-24T22:55:33.170Z",
      "action": "Updated dependency versions"
    }
  ]
}